[
  {
    "date": "2026-06-24",
    "greeting": "Добро јутро — добродошли у среду, 24. јуна 2026. године.",
    "generatedAt": "24.6.26. 09:32",
    "sections": 0,
    "items": 0
  },
  {
    "date": "2026-06-23",
    "greeting": "Добро јутро. Дневни преглед вести за данас.",
    "generatedAt": "23.6.26. 21:45",
    "sections": 5,
    "items": 6
  },
  {
    "date": "2026-06-20",
    "greeting": "Добро јутро. Дневни преглед вести за данас.",
    "generatedAt": "20.6.26. 10:56",
    "sections": 5,
    "items": 6
  }
]